Metadata-Version: 2.1
Name: odoo-addon-pms_l10n_es_sii
Version: 16.0.1.1.0.2
Summary: PMS AEAT SII Integration
Home-page: https://github.com/OCA/pms
Author: Commit [Sun], Odoo Community Association (OCA)
Author-email: support@odoo-community.org
License: AGPL-3
Classifier: Programming Language :: Python
Classifier: Framework :: Odoo
Classifier: Framework :: Odoo :: 16.0
Classifier: License :: OSI Approved :: GNU Affero General Public License v3
Requires-Python: >=3.10
Requires-Dist: odoo-addon-l10n-es-aeat-sii-oca<16.1dev,>=16.0dev
Requires-Dist: odoo-addon-pms<16.1dev,>=16.0dev
Requires-Dist: odoo<16.1dev,>=16.0a
